frozen_django/README.rst
frozen_django/__init__.py
frozen_django/apps.py
frozen_django/main.py
frozen_django/tasks_celery.py
frozen_django/tasks_uwsgi.py
frozen_django/management/__init__.py
frozen_django/management/commands/__init__.py
frozen_django/management/commands/freeze_view.py
frozen_django-1.0.4.dist-info/LICENSE
frozen_django-1.0.4.dist-info/METADATA
frozen_django-1.0.4.dist-info/WHEEL
frozen_django-1.0.4.dist-info/top_level.txt
frozen_django-1.0.4.dist-info/RECORD
