Metadata-Version: 2.1
Name: frozen-django
Version: 1.0.4
Summary: Build html files from Django views.
Home-page: https://github.com/dozymoe/frozen-django
Author: Fahri Reza
Author-email: i@dozy.moe
License: MIT
Project-URL: Bug Tracker, https://github.com/dozymoe/frozen-django/issues
Platform: UNKNOWN
Classifier: Environment :: Web Environment
Classifier: Framework :: Django
Classifier: Intended Audience :: Developers
Classifier: License :: OSI Approved :: MIT License
Classifier: Operating System :: OS Independent
Classifier: Programming Language :: Python
Classifier: Programming Language :: Python :: 3
Classifier: Topic :: Internet :: WWW/HTTP
Classifier: Topic :: Internet :: WWW/HTTP :: Dynamic Content
License-File: LICENSE
